{
  "brands": [
    "bimbo",
    "los sorchantes",
    "maestro cubano",
    "nutrabien",
    "sanissimo",
    "pancatalan",
    "tia rosa",
    "rapiditas",
    "vital",
    "artesano"
  ],
  "groups": {
    "bimbo": [
      "bimbo",
      "los sorchantes",
      "maestro cubano",
      "nutrabien",
      "sanissimo",
      "pancatalan",
      "tia rosa",
      "rapiditas",
      "vital",
      "artesano"
    ]
  },
  "generatedAt": "2026-05-26T01:26:23.281Z",
  "items": [
    {
      "super": "devoto",
      "sku": "660290",
      "name": "Pan BIMBO integral artesano 530g",
      "brand": "artesano",
      "group": "bimbo",
      "price": 195,
      "listPrice": null,
      "currency": "UYU",
      "url": "https://www.devoto.com.uy/product/pan-bimbo-integral-artesano-530g/660290"
    },
    {
      "super": "disco",
      "sku": "660290",
      "name": "Pan BIMBO integral artesano 530g",
      "brand": "artesano",
      "group": "bimbo",
      "price": 195,
      "listPrice": null,
      "currency": "UYU",
      "url": "https://www.disco.com.uy/product/pan-bimbo-integral-artesano-530g/660290"
    },
    {
      "super": "tiendainglesa",
      "sku": "381170",
      "name": "Pan Blanco Artesano BIMBO con Masa Madre 500 gr",
      "brand": "artesano",
      "group": "bimbo",
      "price": 206,
      "listPrice": null,
      "currency": "UYU",
      "url": "https://www.tiendainglesa.com.uy/supermercado/pan-blanco-artesano-bimbo-con-masa-madre-500-gr.producto?381170,,42"
    },
    {
      "super": "tata",
      "sku": "823",
      "name": "Pan Blanco Bimbo Artesano 500 G",
      "brand": "artesano",
      "group": "bimbo",
      "price": 190,
      "listPrice": 190,
      "currency": "UYU",
      "url": "https://www.tata.com.uy/pan-blanco-bimbo-artesano-500-g-823/p"
    },
    {
      "super": "devoto",
      "sku": "660362",
      "name": "Pan blanco BIMBO artesano 540 g",
      "brand": "artesano",
      "group": "bimbo",
      "price": 169,
      "listPrice": null,
      "currency": "UYU",
      "url": "https://www.devoto.com.uy/product/pan-blanco-bimbo-artesano-540-g/660362"
    },
    {
      "super": "disco",
      "sku": "660362",
      "name": "Pan blanco BIMBO artesano 540 g",
      "brand": "artesano",
      "group": "bimbo",
      "price": 169,
      "listPrice": null,
      "currency": "UYU",
      "url": "https://www.disco.com.uy/product/pan-blanco-bimbo-artesano-540-g/660362"
    },
    {
      "super": "devoto",
      "sku": "661630",
      "name": "Pan brioche BIMBO artesano x4 240 g",
      "brand": "artesano",
      "group": "bimbo",
      "price": 123,
      "listPrice": null,
      "currency": "UYU",
      "url": "https://www.devoto.com.uy/product/pan-brioche-bimbo-artesano-x4-240-g/661630"
    },
    {
      "super": "disco",
      "sku": "661630",
      "name": "Pan brioche BIMBO artesano x4 240 g",
      "brand": "artesano",
      "group": "bimbo",
      "price": 123,
      "listPrice": null,
      "currency": "UYU",
      "url": "https://www.disco.com.uy/product/pan-brioche-bimbo-artesano-x4-240-g/661630"
    },
    {
      "super": "tata",
      "sku": "138617",
      "name": "Pan De Papa Bimbo Artesano 4U 300 G",
      "brand": "artesano",
      "group": "bimbo",
      "price": 123,
      "listPrice": 123,
      "currency": "UYU",
      "url": "https://www.tata.com.uy/pan-de-papa-bimbo-artesano-4u-300-g-138617/p"
    },
    {
      "super": "devoto",
      "sku": "663951",
      "name": "Pan de papa para hamburguesa artesano BIMBO 300 g",
      "brand": "artesano",
      "group": "bimbo",
      "price": 123,
      "listPrice": null,
      "currency": "UYU",
      "url": "https://www.devoto.com.uy/product/pan-de-papa-para-hamburguesa-artesano-bimbo-300-g/663951"
    },
    {
      "super": "disco",
      "sku": "663951",
      "name": "Pan de papa para hamburguesa artesano BIMBO 300 g",
      "brand": "artesano",
      "group": "bimbo",
      "price": 123,
      "listPrice": null,
      "currency": "UYU",
      "url": "https://www.disco.com.uy/product/pan-de-papa-para-hamburguesa-artesano-bimbo-300-g/663951"
    },
    {
      "super": "tata",
      "sku": "117854",
      "name": "Pan Hamburguesa Artesano 240 G",
      "brand": "artesano",
      "group": "bimbo",
      "price": 135,
      "listPrice": 135,
      "currency": "UYU",
      "url": "https://www.tata.com.uy/pan-hamburguesa-artesano-240-g-117854/p"
    },
    {
      "super": "tiendainglesa",
      "sku": "1525201",
      "name": "Pan Integral Artesano BIMBO con Masa Madre 530 gr",
      "brand": "artesano",
      "group": "bimbo",
      "price": 239,
      "listPrice": null,
      "currency": "UYU",
      "url": "https://www.tiendainglesa.com.uy/supermercado/pan-integral-artesano-bimbo-con-masa-madre-530-gr.producto?1525201,,42"
    },
    {
      "super": "tata",
      "sku": "86737",
      "name": "Pan Integral Bimbo Artesano 500 G",
      "brand": "artesano",
      "group": "bimbo",
      "price": 191,
      "listPrice": 191,
      "currency": "UYU",
      "url": "https://www.tata.com.uy/pan-integral-bimbo-artesano-500-g-86737/p"
    },
    {
      "super": "devoto",
      "sku": "661650",
      "name": "Pan para hamburguesa x4 BIMBO artesano 240 g",
      "brand": "artesano",
      "group": "bimbo",
      "price": 109,
      "listPrice": null,
      "currency": "UYU",
      "url": "https://www.devoto.com.uy/product/pan-para-hamburguesa-x4-bimbo-artesano-240-g/661650"
    },
    {
      "super": "disco",
      "sku": "661650",
      "name": "Pan para hamburguesa x4 BIMBO artesano 240 g",
      "brand": "artesano",
      "group": "bimbo",
      "price": 109,
      "listPrice": null,
      "currency": "UYU",
      "url": "https://www.disco.com.uy/product/pan-para-hamburguesa-x4-bimbo-artesano-240-g/661650"
    },
    {
      "super": "tiendainglesa",
      "sku": "1541518",
      "name": "Pan Tortuga BIMBO Artesano 4 Unidades",
      "brand": "artesano",
      "group": "bimbo",
      "price": 124,
      "listPrice": null,
      "currency": "UYU",
      "url": "https://www.tiendainglesa.com.uy/supermercado/pan-tortuga-bimbo-artesano-4-unidades.producto?1541518,,42"
    },
    {
      "super": "tiendainglesa",
      "sku": "1560386",
      "name": "Pan Tortuga de Papa Artesano BIMBO 300 gr",
      "brand": "artesano",
      "group": "bimbo",
      "price": 127,
      "listPrice": null,
      "currency": "UYU",
      "url": "https://www.tiendainglesa.com.uy/supermercado/pan-tortuga-de-papa-artesano-bimbo-300-gr.producto?1560386,,42"
    },
    {
      "super": "tata",
      "sku": "152701",
      "name": "Madalena Bimbo Rellena Dulce De Leche 190 G",
      "brand": "bimbo",
      "group": "bimbo",
      "price": 117,
      "listPrice": 117,
      "currency": "UYU",
      "url": "https://www.tata.com.uy/madalena-bimbo-rellena-dulce-de-leche-190-g-152701/p"
    },
    {
      "super": "tata",
      "sku": "152700",
      "name": "Madalenas Bimbo Vainilla 200 G",
      "brand": "bimbo",
      "group": "bimbo",
      "price": 135,
      "listPrice": 135,
      "currency": "UYU",
      "url": "https://www.tata.com.uy/madalenas-bimbo-vainilla-200-g-152700/p"
    },
    {
      "super": "tiendainglesa",
      "sku": "420355",
      "name": "Madalenas Rellenas de Dulce de Leche BIMBO 180 gr",
      "brand": "bimbo",
      "group": "bimbo",
      "price": 143,
      "listPrice": null,
      "currency": "UYU",
      "url": "https://www.tiendainglesa.com.uy/supermercado/madalenas-rellenas-de-dulce-de-leche-bimbo-180-gr.producto?420355,,42"
    },
    {
      "super": "tiendainglesa",
      "sku": "420350",
      "name": "Madalenas Vainilla BIMBO 200 gr",
      "brand": "bimbo",
      "group": "bimbo",
      "price": 144,
      "listPrice": null,
      "currency": "UYU",
      "url": "https://www.tiendainglesa.com.uy/supermercado/madalenas-vainilla-bimbo-200-gr.producto?420350,,42"
    },
    {
      "super": "tiendainglesa",
      "sku": "1565118",
      "name": "Pan BIMBO Lacteado Fuente de Vitamina D 570 gr",
      "brand": "bimbo",
      "group": "bimbo",
      "price": 164,
      "listPrice": null,
      "currency": "UYU",
      "url": "https://www.tiendainglesa.com.uy/supermercado/pan-bimbo-lacteado-fuente-de-vitamina-d-570-gr.producto?1565118,,42"
    },
    {
      "super": "tata",
      "sku": "117856",
      "name": "Pan Blanco Bimbo Cero 500 G",
      "brand": "bimbo",
      "group": "bimbo",
      "price": 183,
      "listPrice": 183,
      "currency": "UYU",
      "url": "https://www.tata.com.uy/pan-blanco-bimbo-cero-500-g-117856/p"
    },
    {
      "super": "tiendainglesa",
      "sku": "1541427",
      "name": "Pan Blanco BIMBO Cero Cero 500 gr",
      "brand": "bimbo",
      "group": "bimbo",
      "price": 199,
      "listPrice": null,
      "currency": "UYU",
      "url": "https://www.tiendainglesa.com.uy/supermercado/pan-blanco-bimbo-cero-cero-500-gr.producto?1541427,,42"
    },
    {
      "super": "devoto",
      "sku": "661652",
      "name": "Pan blanco en rodajas BIMBO cero 500 g",
      "brand": "bimbo",
      "group": "bimbo",
      "price": 192,
      "listPrice": null,
      "currency": "UYU",
      "url": "https://www.devoto.com.uy/product/pan-blanco-en-rodajas-bimbo-cero-500-g/661652"
    },
    {
      "super": "disco",
      "sku": "661652",
      "name": "Pan blanco en rodajas BIMBO cero 500 g",
      "brand": "bimbo",
      "group": "bimbo",
      "price": 192,
      "listPrice": null,
      "currency": "UYU",
      "url": "https://www.disco.com.uy/product/pan-blanco-en-rodajas-bimbo-cero-500-g/661652"
    },
    {
      "super": "tiendainglesa",
      "sku": "1570746",
      "name": "Pan de Viena BIMBO (8 un.) 300 g",
      "brand": "bimbo",
      "group": "bimbo",
      "price": 135,
      "listPrice": null,
      "currency": "UYU",
      "url": "https://www.tiendainglesa.com.uy/supermercado/pan-de-viena-bimbo-8-un.-300-g.producto?1570746,,42"
    },
    {
      "super": "devoto",
      "sku": "601904",
      "name": "Pan de viena BIMBO x8 unidades 300 g",
      "brand": "bimbo",
      "group": "bimbo",
      "price": 134,
      "listPrice": null,
      "currency": "UYU",
      "url": "https://www.devoto.com.uy/product/pan-de-viena-bimbo-x8-unidades-300-g/601904"
    },
    {
      "super": "disco",
      "sku": "601904",
      "name": "Pan de viena BIMBO x8 unidades 300 g",
      "brand": "bimbo",
      "group": "bimbo",
      "price": 134,
      "listPrice": null,
      "currency": "UYU",
      "url": "https://www.disco.com.uy/product/pan-de-viena-bimbo-x8-unidades-300-g/601904"
    },
    {
      "super": "tata",
      "sku": "117853",
      "name": "Pan Hamurguesa Brioche 300 G",
      "brand": "bimbo",
      "group": "bimbo",
      "price": 123,
      "listPrice": 123,
      "currency": "UYU",
      "url": "https://www.tata.com.uy/pan-hamurguesa-brioche-300-g-117853/p"
    },
    {
      "super": "devoto",
      "sku": "602534",
      "name": "Pan Integral BIMBO 620 g",
      "brand": "bimbo",
      "group": "bimbo",
      "price": 186,
      "listPrice": null,
      "currency": "UYU",
      "url": "https://www.devoto.com.uy/product/pan-integral-bimbo-620-g/602534"
    },
    {
      "super": "disco",
      "sku": "602534",
      "name": "Pan Integral BIMBO 620 g",
      "brand": "bimbo",
      "group": "bimbo",
      "price": 186,
      "listPrice": null,
      "currency": "UYU",
      "url": "https://www.disco.com.uy/product/pan-integral-bimbo-620-g/602534"
    },
    {
      "super": "devoto",
      "sku": "661651",
      "name": "Pan integral BIMBO cero 520 g",
      "brand": "bimbo",
      "group": "bimbo",
      "price": 218,
      "listPrice": null,
      "currency": "UYU",
      "url": "https://www.devoto.com.uy/product/pan-integral-bimbo-cero-520-g/661651"
    },
    {
      "super": "disco",
      "sku": "661651",
      "name": "Pan integral BIMBO cero 520 g",
      "brand": "bimbo",
      "group": "bimbo",
      "price": 218,
      "listPrice": null,
      "currency": "UYU",
      "url": "https://www.disco.com.uy/product/pan-integral-bimbo-cero-520-g/661651"
    },
    {
      "super": "tata",
      "sku": "117855",
      "name": "Pan Integral Bimbo Cero 520 G",
      "brand": "bimbo",
      "group": "bimbo",
      "price": 191,
      "listPrice": 191,
      "currency": "UYU",
      "url": "https://www.tata.com.uy/pan-integral-bimbo-cero-520-g-117855/p"
    },
    {
      "super": "tiendainglesa",
      "sku": "1541426",
      "name": "Pan Integral BIMBO Cero Cero 520 gr",
      "brand": "bimbo",
      "group": "bimbo",
      "price": 220,
      "listPrice": null,
      "currency": "UYU",
      "url": "https://www.tiendainglesa.com.uy/supermercado/pan-integral-bimbo-cero-cero-520-gr.producto?1541426,,42"
    },
    {
      "super": "tata",
      "sku": "822",
      "name": "Pan Integral Con Miel Bimbo 660 G",
      "brand": "bimbo",
      "group": "bimbo",
      "price": 159,
      "listPrice": 175,
      "currency": "UYU",
      "url": "https://www.tata.com.uy/pan-integral-con-miel-bimbo-660-g-822/p"
    },
    {
      "super": "tiendainglesa",
      "sku": "331558",
      "name": "Pan Integral con Miel BIMBO 660 gr",
      "brand": "bimbo",
      "group": "bimbo",
      "price": 193,
      "listPrice": null,
      "currency": "UYU",
      "url": "https://www.tiendainglesa.com.uy/supermercado/pan-integral-con-miel-bimbo-660-gr.producto?331558,,42"
    },
    {
      "super": "tiendainglesa",
      "sku": "256646",
      "name": "Pan Lactal Sin Sal BIMBO 330 gr",
      "brand": "bimbo",
      "group": "bimbo",
      "price": 181,
      "listPrice": null,
      "currency": "UYU",
      "url": "https://www.tiendainglesa.com.uy/supermercado/pan-lactal-sin-sal-bimbo-330-gr.producto?256646,,42"
    },
    {
      "super": "tata",
      "sku": "821",
      "name": "Pan Lacteado Bimbo 360 G",
      "brand": "bimbo",
      "group": "bimbo",
      "price": 141,
      "listPrice": 141,
      "currency": "UYU",
      "url": "https://www.tata.com.uy/pan-lacteado-bimbo-360-g-821/p"
    },
    {
      "super": "devoto",
      "sku": "602554",
      "name": "Pan lacteado BIMBO 400 g",
      "brand": "bimbo",
      "group": "bimbo",
      "price": 139,
      "listPrice": null,
      "currency": "UYU",
      "url": "https://www.devoto.com.uy/product/pan-lacteado-bimbo-400-g/602554"
    },
    {
      "super": "disco",
      "sku": "602554",
      "name": "Pan lacteado BIMBO 400 g",
      "brand": "bimbo",
      "group": "bimbo",
      "price": 139,
      "listPrice": null,
      "currency": "UYU",
      "url": "https://www.disco.com.uy/product/pan-lacteado-bimbo-400-g/602554"
    },
    {
      "super": "tata",
      "sku": "820",
      "name": "Pan Lacteado Bimbo 570 G",
      "brand": "bimbo",
      "group": "bimbo",
      "price": 150,
      "listPrice": 162,
      "currency": "UYU",
      "url": "https://www.tata.com.uy/pan-lacteado-bimbo-570-g-820/p"
    },
    {
      "super": "devoto",
      "sku": "602546",
      "name": "Pan Lacteado BIMBO 590 g",
      "brand": "bimbo",
      "group": "bimbo",
      "price": 139,
      "listPrice": 162,
      "currency": "UYU",
      "url": "https://www.devoto.com.uy/product/pan-lacteado-bimbo-590-g/602546"
    },
    {
      "super": "disco",
      "sku": "602546",
      "name": "Pan Lacteado BIMBO 590 g",
      "brand": "bimbo",
      "group": "bimbo",
      "price": 139,
      "listPrice": 162,
      "currency": "UYU",
      "url": "https://www.disco.com.uy/product/pan-lacteado-bimbo-590-g/602546"
    },
    {
      "super": "tata",
      "sku": "7776",
      "name": "Pan Lacteado Bimbo Sin Sal 390 G",
      "brand": "bimbo",
      "group": "bimbo",
      "price": 163,
      "listPrice": 163,
      "currency": "UYU",
      "url": "https://www.tata.com.uy/pan-lacteado-bimbo-sin-sal-390-g-7776/p"
    },
    {
      "super": "tiendainglesa",
      "sku": "330166",
      "name": "Pan Lacteado Mediano BIMBO 360 gr",
      "brand": "bimbo",
      "group": "bimbo",
      "price": 144,
      "listPrice": null,
      "currency": "UYU",
      "url": "https://www.tiendainglesa.com.uy/supermercado/pan-lacteado-mediano-bimbo-360-gr.producto?330166,,42"
    },
    {
      "super": "devoto",
      "sku": "602555",
      "name": "Pan lacteado sin sal BIMBO 400 g",
      "brand": "bimbo",
      "group": "bimbo",
      "price": 175,
      "listPrice": null,
      "currency": "UYU",
      "url": "https://www.devoto.com.uy/product/pan-lacteado-sin-sal-bimbo-400-g/602555"
    },
    {
      "super": "disco",
      "sku": "602555",
      "name": "Pan lacteado sin sal BIMBO 400 g",
      "brand": "bimbo",
      "group": "bimbo",
      "price": 175,
      "listPrice": null,
      "currency": "UYU",
      "url": "https://www.disco.com.uy/product/pan-lacteado-sin-sal-bimbo-400-g/602555"
    },
    {
      "super": "devoto",
      "sku": "201932",
      "name": "Pan tortuga BIMBO 6 un. 300 g",
      "brand": "bimbo",
      "group": "bimbo",
      "price": 134,
      "listPrice": null,
      "currency": "UYU",
      "url": "https://www.devoto.com.uy/product/pan-tortuga-bimbo-6-un-300-g/201932"
    },
    {
      "super": "disco",
      "sku": "201932",
      "name": "Pan tortuga BIMBO 6 un. 300 g",
      "brand": "bimbo",
      "group": "bimbo",
      "price": 134,
      "listPrice": null,
      "currency": "UYU",
      "url": "https://www.disco.com.uy/product/pan-tortuga-bimbo-6-un-300-g/201932"
    },
    {
      "super": "tiendainglesa",
      "sku": "1541517",
      "name": "Pan Tortuga BIMBO Brioche 4 Unidades",
      "brand": "bimbo",
      "group": "bimbo",
      "price": 127,
      "listPrice": null,
      "currency": "UYU",
      "url": "https://www.tiendainglesa.com.uy/supermercado/pan-tortuga-bimbo-brioche-4-unidades.producto?1541517,,42"
    },
    {
      "super": "tata",
      "sku": "3764",
      "name": "Pan Tortuga Bimbo Clásica 6 U",
      "brand": "bimbo",
      "group": "bimbo",
      "price": 119,
      "listPrice": 119,
      "currency": "UYU",
      "url": "https://www.tata.com.uy/pan-tortuga-bimbo-clasica-6-u-3764/p"
    },
    {
      "super": "devoto",
      "sku": "601811",
      "name": "Pan tortuga BIMBO con sésamo x 6 330 g",
      "brand": "bimbo",
      "group": "bimbo",
      "price": 141,
      "listPrice": null,
      "currency": "UYU",
      "url": "https://www.devoto.com.uy/product/pan-tortuga-bimbo-con-sesamo-x-6-330-g/601811"
    },
    {
      "super": "disco",
      "sku": "601811",
      "name": "Pan tortuga BIMBO con sésamo x 6 330 g",
      "brand": "bimbo",
      "group": "bimbo",
      "price": 141,
      "listPrice": null,
      "currency": "UYU",
      "url": "https://www.disco.com.uy/product/pan-tortuga-bimbo-con-sesamo-x-6-330-g/601811"
    },
    {
      "super": "tiendainglesa",
      "sku": "1570745",
      "name": "Pan Tortuga BIMBO Rebanada 0% Colesterol x 6 Unidades 330 gr",
      "brand": "bimbo",
      "group": "bimbo",
      "price": 135,
      "listPrice": null,
      "currency": "UYU",
      "url": "https://www.tiendainglesa.com.uy/supermercado/pan-tortuga-bimbo-rebanada-0%25-colesterol-x-6-unidades-330-gr.producto?1570745,,42"
    },
    {
      "super": "tiendainglesa",
      "sku": "1570713",
      "name": "Pan Tortuga BIMBO Rebanada con Sésamo x 6 Unidades 330 gr",
      "brand": "bimbo",
      "group": "bimbo",
      "price": 146,
      "listPrice": null,
      "currency": "UYU",
      "url": "https://www.tiendainglesa.com.uy/supermercado/pan-tortuga-bimbo-rebanada-con-sesamo-x-6-unidades-330-gr.producto?1570713,,42"
    },
    {
      "super": "tata",
      "sku": "14577",
      "name": "Pan Tortuga Con Sesamo Bimbo 6 U",
      "brand": "bimbo",
      "group": "bimbo",
      "price": 129,
      "listPrice": 129,
      "currency": "UYU",
      "url": "https://www.tata.com.uy/pan-tortuga-con-sesamo-bimbo-6-u-14577/p"
    },
    {
      "super": "tata",
      "sku": "3765",
      "name": "Pan Viena Bimbo Bolsa 8 U",
      "brand": "bimbo",
      "group": "bimbo",
      "price": 119,
      "listPrice": 119,
      "currency": "UYU",
      "url": "https://www.tata.com.uy/pan-viena-bimbo-bolsa-8-u-3765/p"
    },
    {
      "super": "tata",
      "sku": "3776",
      "name": "Vainilla Bimbo 148 G",
      "brand": "bimbo",
      "group": "bimbo",
      "price": 129,
      "listPrice": 129,
      "currency": "UYU",
      "url": "https://www.tata.com.uy/vainilla-bimbo-148-g-3776/p"
    },
    {
      "super": "devoto",
      "sku": "602694",
      "name": "Vainilla BIMBO 74 g",
      "brand": "bimbo",
      "group": "bimbo",
      "price": 73,
      "listPrice": null,
      "currency": "UYU",
      "url": "https://www.devoto.com.uy/product/vainilla-bimbo-74-g/602694"
    },
    {
      "super": "disco",
      "sku": "602694",
      "name": "Vainilla BIMBO 74 g",
      "brand": "bimbo",
      "group": "bimbo",
      "price": 73,
      "listPrice": null,
      "currency": "UYU",
      "url": "https://www.disco.com.uy/product/vainilla-bimbo-74-g/602694"
    },
    {
      "super": "devoto",
      "sku": "660635",
      "name": "Vainillas BIMBO 148 g",
      "brand": "bimbo",
      "group": "bimbo",
      "price": 130,
      "listPrice": null,
      "currency": "UYU",
      "url": "https://www.devoto.com.uy/product/vainillas-bimbo-148-g/660635"
    },
    {
      "super": "disco",
      "sku": "660635",
      "name": "Vainillas BIMBO 148 g",
      "brand": "bimbo",
      "group": "bimbo",
      "price": 130,
      "listPrice": null,
      "currency": "UYU",
      "url": "https://www.disco.com.uy/product/vainillas-bimbo-148-g/660635"
    },
    {
      "super": "tiendainglesa",
      "sku": "410372",
      "name": "Vainillas BIMBO 148g",
      "brand": "bimbo",
      "group": "bimbo",
      "price": 131,
      "listPrice": null,
      "currency": "UYU",
      "url": "https://www.tiendainglesa.com.uy/supermercado/vainillas-bimbo-148g.producto?410372,,42"
    },
    {
      "super": "devoto",
      "sku": "660637",
      "name": "Vainillas BIMBO 444 g",
      "brand": "bimbo",
      "group": "bimbo",
      "price": 279,
      "listPrice": null,
      "currency": "UYU",
      "url": "https://www.devoto.com.uy/product/vainillas-bimbo-444-g/660637"
    },
    {
      "super": "disco",
      "sku": "660637",
      "name": "Vainillas BIMBO 444 g",
      "brand": "bimbo",
      "group": "bimbo",
      "price": 279,
      "listPrice": null,
      "currency": "UYU",
      "url": "https://www.disco.com.uy/product/vainillas-bimbo-444-g/660637"
    },
    {
      "super": "tiendainglesa",
      "sku": "343223",
      "name": "Vainillas BIMBO 480g",
      "brand": "bimbo",
      "group": "bimbo",
      "price": 338,
      "listPrice": null,
      "currency": "UYU",
      "url": "https://www.tiendainglesa.com.uy/supermercado/vainillas-bimbo-480g.producto?343223,,42"
    },
    {
      "super": "tata",
      "sku": "169382",
      "name": "Vainillas Bimbo 74 G",
      "brand": "bimbo",
      "group": "bimbo",
      "price": 63,
      "listPrice": 63,
      "currency": "UYU",
      "url": "https://www.tata.com.uy/vainillas-bimbo-74-g-169382/p"
    },
    {
      "super": "tiendainglesa",
      "sku": "1590865",
      "name": "Vainillas BIMBO 74 gr",
      "brand": "bimbo",
      "group": "bimbo",
      "price": 78,
      "listPrice": null,
      "currency": "UYU",
      "url": "https://www.tiendainglesa.com.uy/supermercado/vainillas-bimbo-74-gr.producto?1590865,,42"
    },
    {
      "super": "devoto",
      "sku": "602318",
      "name": "Pan americano grande LOS SORCHANTES 480 g",
      "brand": "los sorchantes",
      "group": "bimbo",
      "price": 139,
      "listPrice": null,
      "currency": "UYU",
      "url": "https://www.devoto.com.uy/product/pan-americano-grande-los-sorchantes-480-g/602318"
    },
    {
      "super": "disco",
      "sku": "602318",
      "name": "Pan americano grande LOS SORCHANTES 480 g",
      "brand": "los sorchantes",
      "group": "bimbo",
      "price": 139,
      "listPrice": null,
      "currency": "UYU",
      "url": "https://www.disco.com.uy/product/pan-americano-grande-los-sorchantes-480-g/602318"
    },
    {
      "super": "tata",
      "sku": "3757",
      "name": "Pan Americano Los Sorchantes Grande 480 G",
      "brand": "los sorchantes",
      "group": "bimbo",
      "price": 115,
      "listPrice": 131,
      "currency": "UYU",
      "url": "https://www.tata.com.uy/pan-americano-los-sorchantes-grande-480-g-3757/p"
    },
    {
      "super": "tiendainglesa",
      "sku": "4545",
      "name": "Pan de Viena LOS SORCHANTES 8 Unidades 180 gr",
      "brand": "los sorchantes",
      "group": "bimbo",
      "price": 129,
      "listPrice": null,
      "currency": "UYU",
      "url": "https://www.tiendainglesa.com.uy/supermercado/pan-de-viena-los-sorchantes-8-unidades-180-gr.producto?4545,,42"
    },
    {
      "super": "devoto",
      "sku": "601711",
      "name": "Pan integral familiar LOS SORCHANTES 550 g",
      "brand": "los sorchantes",
      "group": "bimbo",
      "price": 169,
      "listPrice": null,
      "currency": "UYU",
      "url": "https://www.devoto.com.uy/product/pan-integral-familiar-los-sorchantes-550-g/601711"
    },
    {
      "super": "disco",
      "sku": "601711",
      "name": "Pan integral familiar LOS SORCHANTES 550 g",
      "brand": "los sorchantes",
      "group": "bimbo",
      "price": 169,
      "listPrice": null,
      "currency": "UYU",
      "url": "https://www.disco.com.uy/product/pan-integral-familiar-los-sorchantes-550-g/601711"
    },
    {
      "super": "tiendainglesa",
      "sku": "1565117",
      "name": "Pan Integral LOS SORCHANTES 550 gr",
      "brand": "los sorchantes",
      "group": "bimbo",
      "price": 171,
      "listPrice": null,
      "currency": "UYU",
      "url": "https://www.tiendainglesa.com.uy/supermercado/pan-integral-los-sorchantes-550-gr.producto?1565117,,42"
    },
    {
      "super": "tata",
      "sku": "3759",
      "name": "Pan Integral Los Sorchantes Familiar 570 G",
      "brand": "los sorchantes",
      "group": "bimbo",
      "price": 125,
      "listPrice": 169,
      "currency": "UYU",
      "url": "https://www.tata.com.uy/pan-integral-los-sorchantes-familiar-570-g-3759/p"
    },
    {
      "super": "tiendainglesa",
      "sku": "1565871",
      "name": "Pan Lacteado LOS SORCHANTES 480 gr",
      "brand": "los sorchantes",
      "group": "bimbo",
      "price": 140,
      "listPrice": null,
      "currency": "UYU",
      "url": "https://www.tiendainglesa.com.uy/supermercado/pan-lacteado-los-sorchantes-480-gr.producto?1565871,,42"
    },
    {
      "super": "tata",
      "sku": "136772",
      "name": "Pan Rallado Comun Los Sorchantes 400 G",
      "brand": "los sorchantes",
      "group": "bimbo",
      "price": 125,
      "listPrice": 125,
      "currency": "UYU",
      "url": "https://www.tata.com.uy/pan-rallado-comun-los-sorchantes-400-g-136772/p"
    },
    {
      "super": "tata",
      "sku": "136770",
      "name": "Pan Rallado Los Sorchante Saborizado 800 G",
      "brand": "los sorchantes",
      "group": "bimbo",
      "price": 195,
      "listPrice": 195,
      "currency": "UYU",
      "url": "https://www.tata.com.uy/pan-rallado-los-sorchante-saborizado-800-g-136770/p"
    },
    {
      "super": "devoto",
      "sku": "346268",
      "name": "Pan rallado LOS SORCHANTES 400 g",
      "brand": "los sorchantes",
      "group": "bimbo",
      "price": 125,
      "listPrice": null,
      "currency": "UYU",
      "url": "https://www.devoto.com.uy/product/pan-rallado-los-sorchantes-400-g/346268"
    },
    {
      "super": "disco",
      "sku": "346268",
      "name": "Pan rallado LOS SORCHANTES 400 g",
      "brand": "los sorchantes",
      "group": "bimbo",
      "price": 125,
      "listPrice": null,
      "currency": "UYU",
      "url": "https://www.disco.com.uy/product/pan-rallado-los-sorchantes-400-g/346268"
    },
    {
      "super": "devoto",
      "sku": "346269",
      "name": "Pan rallado LOS SORCHANTES 800 g",
      "brand": "los sorchantes",
      "group": "bimbo",
      "price": 189,
      "listPrice": null,
      "currency": "UYU",
      "url": "https://www.devoto.com.uy/product/pan-rallado-los-sorchantes-800-g/346269"
    },
    {
      "super": "disco",
      "sku": "346269",
      "name": "Pan rallado LOS SORCHANTES 800 g",
      "brand": "los sorchantes",
      "group": "bimbo",
      "price": 187,
      "listPrice": null,
      "currency": "UYU",
      "url": "https://www.disco.com.uy/product/pan-rallado-los-sorchantes-800-g/346269"
    },
    {
      "super": "tiendainglesa",
      "sku": "1545589",
      "name": "Pan Rallado LOS SORCHANTES 800 gr",
      "brand": "los sorchantes",
      "group": "bimbo",
      "price": 191,
      "listPrice": null,
      "currency": "UYU",
      "url": "https://www.tiendainglesa.com.uy/supermercado/pan-rallado-los-sorchantes-800-gr.producto?1545589,,42"
    },
    {
      "super": "tata",
      "sku": "136769",
      "name": "Pan Rallado Los Sorchantes Comun 800 G",
      "brand": "los sorchantes",
      "group": "bimbo",
      "price": 185,
      "listPrice": 185,
      "currency": "UYU",
      "url": "https://www.tata.com.uy/pan-rallado-los-sorchantes-comun-800-g-136769/p"
    },
    {
      "super": "tiendainglesa",
      "sku": "1545590",
      "name": "Pan Rallado LOS SORCHANTES Saborizado 800 gr",
      "brand": "los sorchantes",
      "group": "bimbo",
      "price": 198,
      "listPrice": null,
      "currency": "UYU",
      "url": "https://www.tiendainglesa.com.uy/supermercado/pan-rallado-los-sorchantes-saborizado-800-gr.producto?1545590,,42"
    },
    {
      "super": "devoto",
      "sku": "346270",
      "name": "Pan rallado saborizado LOS SORCHANTES 400 g",
      "brand": "los sorchantes",
      "group": "bimbo",
      "price": 130,
      "listPrice": null,
      "currency": "UYU",
      "url": "https://www.devoto.com.uy/product/pan-rallado-saborizado-los-sorchantes-400-g/346270"
    },
    {
      "super": "disco",
      "sku": "346270",
      "name": "Pan rallado saborizado LOS SORCHANTES 400 g",
      "brand": "los sorchantes",
      "group": "bimbo",
      "price": 130,
      "listPrice": null,
      "currency": "UYU",
      "url": "https://www.disco.com.uy/product/pan-rallado-saborizado-los-sorchantes-400-g/346270"
    },
    {
      "super": "tata",
      "sku": "136768",
      "name": "Pan Rallado Saborizado Los Sorchantes 400 G",
      "brand": "los sorchantes",
      "group": "bimbo",
      "price": 130,
      "listPrice": 130,
      "currency": "UYU",
      "url": "https://www.tata.com.uy/pan-rallado-saborizado-los-sorchantes-400-g-136768/p"
    },
    {
      "super": "devoto",
      "sku": "346271",
      "name": "Pan rallado saborizado LOS SORCHANTES 800 g",
      "brand": "los sorchantes",
      "group": "bimbo",
      "price": 196,
      "listPrice": null,
      "currency": "UYU",
      "url": "https://www.devoto.com.uy/product/pan-rallado-saborizado-los-sorchantes-800-g/346271"
    },
    {
      "super": "disco",
      "sku": "346271",
      "name": "Pan rallado saborizado LOS SORCHANTES 800 g",
      "brand": "los sorchantes",
      "group": "bimbo",
      "price": 196,
      "listPrice": null,
      "currency": "UYU",
      "url": "https://www.disco.com.uy/product/pan-rallado-saborizado-los-sorchantes-800-g/346271"
    },
    {
      "super": "devoto",
      "sku": "602383",
      "name": "Pan Tortuga LOS SORCHANTES 6 un.",
      "brand": "los sorchantes",
      "group": "bimbo",
      "price": 125,
      "listPrice": null,
      "currency": "UYU",
      "url": "https://www.devoto.com.uy/product/pan-tortuga-los-sorchantes-6-un/602383"
    },
    {
      "super": "disco",
      "sku": "602383",
      "name": "Pan Tortuga LOS SORCHANTES 6 un.",
      "brand": "los sorchantes",
      "group": "bimbo",
      "price": 125,
      "listPrice": null,
      "currency": "UYU",
      "url": "https://www.disco.com.uy/product/pan-tortuga-los-sorchantes-6-un/602383"
    },
    {
      "super": "tiendainglesa",
      "sku": "4547",
      "name": "Pan Tortuga LOS SORCHANTES 6 Unidades 280 gr",
      "brand": "los sorchantes",
      "group": "bimbo",
      "price": 126,
      "listPrice": null,
      "currency": "UYU",
      "url": "https://www.tiendainglesa.com.uy/supermercado/pan-tortuga-los-sorchantes-6-unidades-280-gr.producto?4547,,42"
    },
    {
      "super": "tata",
      "sku": "832",
      "name": "Pan Tortuga Los Sorchantes Clásica 6 U",
      "brand": "los sorchantes",
      "group": "bimbo",
      "price": 122,
      "listPrice": 122,
      "currency": "UYU",
      "url": "https://www.tata.com.uy/pan-tortuga-los-sorchantes-clasica-6-u-832/p"
    },
    {
      "super": "tata",
      "sku": "828",
      "name": "Pan Viena Los Sorchantes 180 G",
      "brand": "los sorchantes",
      "group": "bimbo",
      "price": 122,
      "listPrice": 122,
      "currency": "UYU",
      "url": "https://www.tata.com.uy/pan-viena-los-sorchantes-180-g-828/p"
    },
    {
      "super": "devoto",
      "sku": "602385",
      "name": "Pan Viena LOS SORCHANTES 8 un 210 g",
      "brand": "los sorchantes",
      "group": "bimbo",
      "price": 125,
      "listPrice": null,
      "currency": "UYU",
      "url": "https://www.devoto.com.uy/product/pan-viena-los-sorchantes-8-un-210-g/602385"
    },
    {
      "super": "disco",
      "sku": "602385",
      "name": "Pan Viena LOS SORCHANTES 8 un 210 g",
      "brand": "los sorchantes",
      "group": "bimbo",
      "price": 125,
      "listPrice": null,
      "currency": "UYU",
      "url": "https://www.disco.com.uy/product/pan-viena-los-sorchantes-8-un-210-g/602385"
    },
    {
      "super": "tiendainglesa",
      "sku": "1521099",
      "name": "Galleta Mini Cracker Semillas MAESTRO CUBANO 300 gr",
      "brand": "maestro cubano",
      "group": "bimbo",
      "price": 132,
      "listPrice": null,
      "currency": "UYU",
      "url": "https://www.tiendainglesa.com.uy/supermercado/galleta-mini-cracker-semillas-maestro-cubano-300-gr.producto?1521099,,42"
    },
    {
      "super": "tiendainglesa",
      "sku": "1521082",
      "name": "Galletas Cuban Cracker al Agua MAESTRO CUBANO 330 gr",
      "brand": "maestro cubano",
      "group": "bimbo",
      "price": 126,
      "listPrice": null,
      "currency": "UYU",
      "url": "https://www.tiendainglesa.com.uy/supermercado/galletas-cuban-cracker-al-agua-maestro-cubano-330-gr.producto?1521082,,42"
    },
    {
      "super": "tiendainglesa",
      "sku": "1554137",
      "name": "Galletas Gran Dulce Sabor Vainilla MAESTRO CUBANO 400 gr",
      "brand": "maestro cubano",
      "group": "bimbo",
      "price": 122,
      "listPrice": null,
      "currency": "UYU",
      "url": "https://www.tiendainglesa.com.uy/supermercado/galletas-gran-dulce-sabor-vainilla-maestro-cubano-400-gr.producto?1554137,,42"
    },
    {
      "super": "devoto",
      "sku": "665270",
      "name": "Galletas MAESTRO CUBANO cuban cracker 330 g",
      "brand": "maestro cubano",
      "group": "bimbo",
      "price": 118,
      "listPrice": null,
      "currency": "UYU",
      "url": "https://www.devoto.com.uy/product/galletas-maestro-cubano-cuban-cracker-330-g/665270"
    },
    {
      "super": "disco",
      "sku": "665270",
      "name": "Galletas MAESTRO CUBANO cuban cracker 330 g",
      "brand": "maestro cubano",
      "group": "bimbo",
      "price": 118,
      "listPrice": null,
      "currency": "UYU",
      "url": "https://www.disco.com.uy/product/galletas-maestro-cubano-cuban-cracker-330-g/665270"
    },
    {
      "super": "tata",
      "sku": "86738",
      "name": "Galletas Maestro Cubano Cuban Cracker 330 G",
      "brand": "maestro cubano",
      "group": "bimbo",
      "price": 128,
      "listPrice": 128,
      "currency": "UYU",
      "url": "https://www.tata.com.uy/galletas-maestro-cubano-cuban-cracker-330-g-86738/p"
    },
    {
      "super": "devoto",
      "sku": "665264",
      "name": "Galletas MAESTRO CUBANO mini crackers 300 g",
      "brand": "maestro cubano",
      "group": "bimbo",
      "price": 118,
      "listPrice": null,
      "currency": "UYU",
      "url": "https://www.devoto.com.uy/product/galletas-maestro-cubano-mini-crackers-300-g/665264"
    },
    {
      "super": "disco",
      "sku": "665264",
      "name": "Galletas MAESTRO CUBANO mini crackers 300 g",
      "brand": "maestro cubano",
      "group": "bimbo",
      "price": 118,
      "listPrice": null,
      "currency": "UYU",
      "url": "https://www.disco.com.uy/product/galletas-maestro-cubano-mini-crackers-300-g/665264"
    },
    {
      "super": "devoto",
      "sku": "665055",
      "name": "Galletas MAESTRO CUBANO salvado tripack 360 g",
      "brand": "maestro cubano",
      "group": "bimbo",
      "price": 138,
      "listPrice": null,
      "currency": "UYU",
      "url": "https://www.devoto.com.uy/product/galletas-maestro-cubano-salvado-tripack-360-g/665055"
    },
    {
      "super": "disco",
      "sku": "665055",
      "name": "Galletas MAESTRO CUBANO salvado tripack 360 g",
      "brand": "maestro cubano",
      "group": "bimbo",
      "price": 138,
      "listPrice": null,
      "currency": "UYU",
      "url": "https://www.disco.com.uy/product/galletas-maestro-cubano-salvado-tripack-360-g/665055"
    },
    {
      "super": "devoto",
      "sku": "665271",
      "name": "Galletas MAESTRO CUBANO selección de semillas 375 g",
      "brand": "maestro cubano",
      "group": "bimbo",
      "price": 162,
      "listPrice": null,
      "currency": "UYU",
      "url": "https://www.devoto.com.uy/product/galletas-maestro-cubano-seleccion-de-semillas-375-g/665271"
    },
    {
      "super": "disco",
      "sku": "665271",
      "name": "Galletas MAESTRO CUBANO selección de semillas 375 g",
      "brand": "maestro cubano",
      "group": "bimbo",
      "price": 162,
      "listPrice": null,
      "currency": "UYU",
      "url": "https://www.disco.com.uy/product/galletas-maestro-cubano-seleccion-de-semillas-375-g/665271"
    },
    {
      "super": "tata",
      "sku": "3735",
      "name": "Galletas Marie El Maestro Cubano 345 G",
      "brand": "maestro cubano",
      "group": "bimbo",
      "price": 154,
      "listPrice": 154,
      "currency": "UYU",
      "url": "https://www.tata.com.uy/galletas-marie-el-maestro-cubano-345-g-3735/p"
    },
    {
      "super": "tata",
      "sku": "86717",
      "name": "Galletas Salvado Maestro Cubano Tripack 360 G",
      "brand": "maestro cubano",
      "group": "bimbo",
      "price": 128,
      "listPrice": 128,
      "currency": "UYU",
      "url": "https://www.tata.com.uy/galletas-salvado-maestro-cubano-tripack-360-g-86717/p"
    },
    {
      "super": "tiendainglesa",
      "sku": "1521086",
      "name": "Galletas Salvado Tripack MAESTRO CUBANO 360 gr",
      "brand": "maestro cubano",
      "group": "bimbo",
      "price": 149,
      "listPrice": null,
      "currency": "UYU",
      "url": "https://www.tiendainglesa.com.uy/supermercado/galletas-salvado-tripack-maestro-cubano-360-gr.producto?1521086,,42"
    },
    {
      "super": "tiendainglesa",
      "sku": "1521083",
      "name": "Galletas Selección de Semillas MAESTRO CUBANO 375 gr",
      "brand": "maestro cubano",
      "group": "bimbo",
      "price": 174,
      "listPrice": null,
      "currency": "UYU",
      "url": "https://www.tiendainglesa.com.uy/supermercado/galletas-seleccion-de-semillas-maestro-cubano-375-gr.producto?1521083,,42"
    },
    {
      "super": "tata",
      "sku": "136863",
      "name": "Galletitas Gran Dulce Vainilla Maestro Cubano 400 G",
      "brand": "maestro cubano",
      "group": "bimbo",
      "price": 122,
      "listPrice": 122,
      "currency": "UYU",
      "url": "https://www.tata.com.uy/galletitas-gran-dulce-vainilla-maestro-cubano-400-g-136863/p"
    },
    {
      "super": "devoto",
      "sku": "665168",
      "name": "Galletitas María MAESTRO CUBANO 345 g",
      "brand": "maestro cubano",
      "group": "bimbo",
      "price": 151,
      "listPrice": null,
      "currency": "UYU",
      "url": "https://www.devoto.com.uy/product/galletitas-maria-maestro-cubano-345-g/665168"
    },
    {
      "super": "disco",
      "sku": "665168",
      "name": "Galletitas María MAESTRO CUBANO 345 g",
      "brand": "maestro cubano",
      "group": "bimbo",
      "price": 151,
      "listPrice": null,
      "currency": "UYU",
      "url": "https://www.disco.com.uy/product/galletitas-maria-maestro-cubano-345-g/665168"
    },
    {
      "super": "tata",
      "sku": "18253",
      "name": "Grisines Con Queso Maestro Cubano 100 G",
      "brand": "maestro cubano",
      "group": "bimbo",
      "price": 99,
      "listPrice": 99,
      "currency": "UYU",
      "url": "https://www.tata.com.uy/grisines-con-queso-maestro-cubano-100-g-18253/p"
    },
    {
      "super": "tiendainglesa",
      "sku": "18976",
      "name": "Grisines Finitos al Agua EL MAESTRO CUBANO 100 gr",
      "brand": "maestro cubano",
      "group": "bimbo",
      "price": 120,
      "listPrice": null,
      "currency": "UYU",
      "url": "https://www.tiendainglesa.com.uy/supermercado/grisines-finitos-al-agua-el-maestro-cubano-100-gr.producto?18976,,42"
    },
    {
      "super": "tata",
      "sku": "747",
      "name": "Grisines Finitos con Salvado El Maestro Cubano 100 G",
      "brand": "maestro cubano",
      "group": "bimbo",
      "price": 99,
      "listPrice": 99,
      "currency": "UYU",
      "url": "https://www.tata.com.uy/grisines-finitos-con-salvado-el-maestro-cubano-100-g-747/p"
    },
    {
      "super": "tiendainglesa",
      "sku": "18977",
      "name": "Grisines Finitos con Salvado EL MAESTRO CUBANO 100 gr",
      "brand": "maestro cubano",
      "group": "bimbo",
      "price": 120,
      "listPrice": null,
      "currency": "UYU",
      "url": "https://www.tiendainglesa.com.uy/supermercado/grisines-finitos-con-salvado-el-maestro-cubano-100-gr.producto?18977,,42"
    },
    {
      "super": "tiendainglesa",
      "sku": "18978",
      "name": "Grisines Finitos de Queso EL MAESTRO CUBANO 100 gr",
      "brand": "maestro cubano",
      "group": "bimbo",
      "price": 120,
      "listPrice": null,
      "currency": "UYU",
      "url": "https://www.tiendainglesa.com.uy/supermercado/grisines-finitos-de-queso-el-maestro-cubano-100-gr.producto?18978,,42"
    },
    {
      "super": "tata",
      "sku": "746",
      "name": "Grisines Finitos El Maestro Cubano 100 G",
      "brand": "maestro cubano",
      "group": "bimbo",
      "price": 99,
      "listPrice": 99,
      "currency": "UYU",
      "url": "https://www.tata.com.uy/grisines-finitos-el-maestro-cubano-100-g-746/p"
    },
    {
      "super": "tata",
      "sku": "3685",
      "name": "Grisines Gourmet Maestro Cibulette y Manteca 120 G",
      "brand": "maestro cubano",
      "group": "bimbo",
      "price": 137,
      "listPrice": 137,
      "currency": "UYU",
      "url": "https://www.tata.com.uy/grisines-gourmet-maestro-cibulette-y-manteca-120-g-3685/p"
    },
    {
      "super": "tata",
      "sku": "3689",
      "name": "Grisines Gourmet Maestro Cubano Cebolla 120 G",
      "brand": "maestro cubano",
      "group": "bimbo",
      "price": 137,
      "listPrice": 137,
      "currency": "UYU",
      "url": "https://www.tata.com.uy/grisines-gourmet-maestro-cubano-cebolla-120-g-3689/p"
    },
    {
      "super": "devoto",
      "sku": "661557",
      "name": "Grisines gourmet MAESTRO CUBANO cebollas asadas",
      "brand": "maestro cubano",
      "group": "bimbo",
      "price": 120,
      "listPrice": null,
      "currency": "UYU",
      "url": "https://www.devoto.com.uy/product/grisines-gourmet-maestro-cubano-cebollas-asadas/661557"
    },
    {
      "super": "disco",
      "sku": "661557",
      "name": "Grisines gourmet MAESTRO CUBANO cebollas asadas",
      "brand": "maestro cubano",
      "group": "bimbo",
      "price": 120,
      "listPrice": null,
      "currency": "UYU",
      "url": "https://www.disco.com.uy/product/grisines-gourmet-maestro-cubano-cebollas-asadas/661557"
    },
    {
      "super": "devoto",
      "sku": "661561",
      "name": "Grisines gourmet MAESTRO CUBANO manteca ciboulette",
      "brand": "maestro cubano",
      "group": "bimbo",
      "price": 120,
      "listPrice": null,
      "currency": "UYU",
      "url": "https://www.devoto.com.uy/product/grisines-gourmet-maestro-cubano-manteca-ciboulette/661561"
    },
    {
      "super": "disco",
      "sku": "661561",
      "name": "Grisines gourmet MAESTRO CUBANO manteca ciboulette",
      "brand": "maestro cubano",
      "group": "bimbo",
      "price": 120,
      "listPrice": null,
      "currency": "UYU",
      "url": "https://www.disco.com.uy/product/grisines-gourmet-maestro-cubano-manteca-ciboulette/661561"
    },
    {
      "super": "tata",
      "sku": "3686",
      "name": "Grisines Gourmet Maestro Cubano Romero 120 G",
      "brand": "maestro cubano",
      "group": "bimbo",
      "price": 137,
      "listPrice": 137,
      "currency": "UYU",
      "url": "https://www.tata.com.uy/grisines-gourmet-maestro-cubano-romero-120-g-3686/p"
    },
    {
      "super": "devoto",
      "sku": "661559",
      "name": "Grisines gourmet MAESTRO CUBANO romero y oliva",
      "brand": "maestro cubano",
      "group": "bimbo",
      "price": 120,
      "listPrice": null,
      "currency": "UYU",
      "url": "https://www.devoto.com.uy/product/grisines-gourmet-maestro-cubano-romero-y-oliva/661559"
    },
    {
      "super": "disco",
      "sku": "661559",
      "name": "Grisines gourmet MAESTRO CUBANO romero y oliva",
      "brand": "maestro cubano",
      "group": "bimbo",
      "price": 120,
      "listPrice": null,
      "currency": "UYU",
      "url": "https://www.disco.com.uy/product/grisines-gourmet-maestro-cubano-romero-y-oliva/661559"
    },
    {
      "super": "tiendainglesa",
      "sku": "363201",
      "name": "Grisines MAESTRO CUBANO Gourmet Cebollas Asadas 120 gr",
      "brand": "maestro cubano",
      "group": "bimbo",
      "price": 128,
      "listPrice": null,
      "currency": "UYU",
      "url": "https://www.tiendainglesa.com.uy/supermercado/grisines-maestro-cubano-gourmet-cebollas-asadas-120-gr.producto?363201,,42"
    },
    {
      "super": "tiendainglesa",
      "sku": "363204",
      "name": "Grisines MAESTRO CUBANO Gourmet Manteca y Ciboulette 120 gr",
      "brand": "maestro cubano",
      "group": "bimbo",
      "price": 128,
      "listPrice": null,
      "currency": "UYU",
      "url": "https://www.tiendainglesa.com.uy/supermercado/grisines-maestro-cubano-gourmet-manteca-y-ciboulette-120-gr.producto?363204,,42"
    },
    {
      "super": "tiendainglesa",
      "sku": "363203",
      "name": "Grisines MAESTRO CUBANO Gourmet Romero y Oliva 120 gr",
      "brand": "maestro cubano",
      "group": "bimbo",
      "price": 128,
      "listPrice": null,
      "currency": "UYU",
      "url": "https://www.tiendainglesa.com.uy/supermercado/grisines-maestro-cubano-gourmet-romero-y-oliva-120-gr.producto?363203,,42"
    },
    {
      "super": "devoto",
      "sku": "744985",
      "name": "Grissines Finitos MAESTRO CUBANO Al Agua",
      "brand": "maestro cubano",
      "group": "bimbo",
      "price": 116,
      "listPrice": null,
      "currency": "UYU",
      "url": "https://www.devoto.com.uy/product/grissines-finitos-maestro-cubano-al-agua/744985"
    },
    {
      "super": "disco",
      "sku": "744985",
      "name": "Grissines Finitos MAESTRO CUBANO Al Agua",
      "brand": "maestro cubano",
      "group": "bimbo",
      "price": 116,
      "listPrice": null,
      "currency": "UYU",
      "url": "https://www.disco.com.uy/product/grissines-finitos-maestro-cubano-al-agua/744985"
    },
    {
      "super": "devoto",
      "sku": "744177",
      "name": "Grissines Finitos MAESTRO CUBANO Integral 100 g",
      "brand": "maestro cubano",
      "group": "bimbo",
      "price": 116,
      "listPrice": null,
      "currency": "UYU",
      "url": "https://www.devoto.com.uy/product/grissines-finitos-maestro-cubano-integral-100-g/744177"
    },
    {
      "super": "disco",
      "sku": "744177",
      "name": "Grissines Finitos MAESTRO CUBANO Integral 100 g",
      "brand": "maestro cubano",
      "group": "bimbo",
      "price": 116,
      "listPrice": null,
      "currency": "UYU",
      "url": "https://www.disco.com.uy/product/grissines-finitos-maestro-cubano-integral-100-g/744177"
    },
    {
      "super": "devoto",
      "sku": "744997",
      "name": "Grissines Finitos MAESTRO CUBANO Queso 100 g",
      "brand": "maestro cubano",
      "group": "bimbo",
      "price": 116,
      "listPrice": null,
      "currency": "UYU",
      "url": "https://www.devoto.com.uy/product/grissines-finitos-maestro-cubano-queso-100-g/744997"
    },
    {
      "super": "disco",
      "sku": "744997",
      "name": "Grissines Finitos MAESTRO CUBANO Queso 100 g",
      "brand": "maestro cubano",
      "group": "bimbo",
      "price": 116,
      "listPrice": null,
      "currency": "UYU",
      "url": "https://www.disco.com.uy/product/grissines-finitos-maestro-cubano-queso-100-g/744997"
    },
    {
      "super": "tata",
      "sku": "743",
      "name": "Habanitos Al Agua El Maestro Cubano 180 G",
      "brand": "maestro cubano",
      "group": "bimbo",
      "price": 113,
      "listPrice": 113,
      "currency": "UYU",
      "url": "https://www.tata.com.uy/habanitos-al-agua-el-maestro-cubano-180-g-743/p"
    },
    {
      "super": "tata",
      "sku": "745",
      "name": "Habanitos De Jamón El Maestro Cubano 180 G",
      "brand": "maestro cubano",
      "group": "bimbo",
      "price": 128,
      "listPrice": 128,
      "currency": "UYU",
      "url": "https://www.tata.com.uy/habanitos-de-jamon-el-maestro-cubano-180-g-745/p"
    },
    {
      "super": "tata",
      "sku": "744",
      "name": "Habanitos De Queso El Maestro Cubano 180 G",
      "brand": "maestro cubano",
      "group": "bimbo",
      "price": 132,
      "listPrice": 132,
      "currency": "UYU",
      "url": "https://www.tata.com.uy/habanitos-de-queso-el-maestro-cubano-180-g-744/p"
    },
    {
      "super": "tiendainglesa",
      "sku": "10999",
      "name": "Habanitos EL MAESTRO CUBANO al Agua 180g",
      "brand": "maestro cubano",
      "group": "bimbo",
      "price": 150,
      "listPrice": null,
      "currency": "UYU",
      "url": "https://www.tiendainglesa.com.uy/supermercado/habanitos-el-maestro-cubano-al-agua-180g.producto?10999,,42"
    },
    {
      "super": "tiendainglesa",
      "sku": "69735",
      "name": "Habanitos EL MAESTRO CUBANO de Jamón 180g",
      "brand": "maestro cubano",
      "group": "bimbo",
      "price": 150,
      "listPrice": null,
      "currency": "UYU",
      "url": "https://www.tiendainglesa.com.uy/supermercado/habanitos-el-maestro-cubano-de-jamon-180g.producto?69735,,42"
    },
    {
      "super": "tiendainglesa",
      "sku": "69737",
      "name": "Habanitos EL MAESTRO CUBANO de Queso 180g",
      "brand": "maestro cubano",
      "group": "bimbo",
      "price": 150,
      "listPrice": null,
      "currency": "UYU",
      "url": "https://www.tiendainglesa.com.uy/supermercado/habanitos-el-maestro-cubano-de-queso-180g.producto?69737,,42"
    },
    {
      "super": "devoto",
      "sku": "662895",
      "name": "Brownie bañado NUTRA BIEN brownie chocolate 35 g",
      "brand": "nutrabien",
      "group": "bimbo",
      "price": 42,
      "listPrice": null,
      "currency": "UYU",
      "url": "https://www.devoto.com.uy/product/brownie-banado-nutra-bien-brownie-chocolate-35-g/662895"
    },
    {
      "super": "disco",
      "sku": "662895",
      "name": "Brownie bañado NUTRA BIEN brownie chocolate 35 g",
      "brand": "nutrabien",
      "group": "bimbo",
      "price": 42,
      "listPrice": null,
      "currency": "UYU",
      "url": "https://www.disco.com.uy/product/brownie-banado-nutra-bien-brownie-chocolate-35-g/662895"
    },
    {
      "super": "tiendainglesa",
      "sku": "1515784",
      "name": "Brownie de Chocolate NUTRA BIEN 35 gr",
      "brand": "nutrabien",
      "group": "bimbo",
      "price": 45,
      "listPrice": null,
      "currency": "UYU",
      "url": "https://www.tiendainglesa.com.uy/supermercado/brownie-de-chocolate-nutra-bien-35-gr.producto?1515784,,42"
    },
    {
      "super": "tiendainglesa",
      "sku": "1515781",
      "name": "Brownie Nuez NUTRA BIEN 62 gr",
      "brand": "nutrabien",
      "group": "bimbo",
      "price": 56,
      "listPrice": null,
      "currency": "UYU",
      "url": "https://www.tiendainglesa.com.uy/supermercado/brownie-nuez-nutra-bien-62-gr.producto?1515781,,42"
    },
    {
      "super": "devoto",
      "sku": "662894",
      "name": "Brownie NUTRA BIEN 62 g",
      "brand": "nutrabien",
      "group": "bimbo",
      "price": 52,
      "listPrice": null,
      "currency": "UYU",
      "url": "https://www.devoto.com.uy/product/brownie-nutra-bien-62-g/662894"
    },
    {
      "super": "disco",
      "sku": "662894",
      "name": "Brownie NUTRA BIEN 62 g",
      "brand": "nutrabien",
      "group": "bimbo",
      "price": 52,
      "listPrice": null,
      "currency": "UYU",
      "url": "https://www.disco.com.uy/product/brownie-nutra-bien-62-g/662894"
    },
    {
      "super": "tata",
      "sku": "149195",
      "name": "Brownie Nutrabien Sin Azucar 50 G",
      "brand": "nutrabien",
      "group": "bimbo",
      "price": 72,
      "listPrice": 72,
      "currency": "UYU",
      "url": "https://www.tata.com.uy/brownie-nutrabien-sin-azucar-50-g-149195/p"
    },
    {
      "super": "devoto",
      "sku": "601416",
      "name": "Brownie sin azucar NUTRABIEN 50 g",
      "brand": "nutrabien",
      "group": "bimbo",
      "price": 77,
      "listPrice": null,
      "currency": "UYU",
      "url": "https://www.devoto.com.uy/product/brownie-sin-azucar-nutrabien-50-g/601416"
    },
    {
      "super": "disco",
      "sku": "601416",
      "name": "Brownie sin azucar NUTRABIEN 50 g",
      "brand": "nutrabien",
      "group": "bimbo",
      "price": 77,
      "listPrice": null,
      "currency": "UYU",
      "url": "https://www.disco.com.uy/product/brownie-sin-azucar-nutrabien-50-g/601416"
    },
    {
      "super": "tata",
      "sku": "86792",
      "name": "Browniechoc Nutrabien 35 G",
      "brand": "nutrabien",
      "group": "bimbo",
      "price": 40,
      "listPrice": 40,
      "currency": "UYU",
      "url": "https://www.tata.com.uy/browniechoc-nutrabien-35-g-86792/p"
    },
    {
      "super": "tiendainglesa",
      "sku": "1562146",
      "name": "Galleta NUTRA BIEN Avena y Manzana 175 gr",
      "brand": "nutrabien",
      "group": "bimbo",
      "price": 82,
      "listPrice": 136,
      "currency": "UYU",
      "url": "https://www.tiendainglesa.com.uy/supermercado/galleta-nutra-bien-avena-y-manzana-175-gr.producto?1562146,,42"
    },
    {
      "super": "tiendainglesa",
      "sku": "1562147",
      "name": "Galleta NUTRA BIEN Avena y Pasas 175 gr",
      "brand": "nutrabien",
      "group": "bimbo",
      "price": 82,
      "listPrice": 136,
      "currency": "UYU",
      "url": "https://www.tiendainglesa.com.uy/supermercado/galleta-nutra-bien-avena-y-pasas-175-gr.producto?1562147,,42"
    },
    {
      "super": "devoto",
      "sku": "601427",
      "name": "Galletas avena y chocolate NUTRABIEN 175 g",
      "brand": "nutrabien",
      "group": "bimbo",
      "price": 131,
      "listPrice": null,
      "currency": "UYU",
      "url": "https://www.devoto.com.uy/product/galletas-avena-y-chocolate-nutrabien-175-g/601427"
    },
    {
      "super": "disco",
      "sku": "601427",
      "name": "Galletas avena y chocolate NUTRABIEN 175 g",
      "brand": "nutrabien",
      "group": "bimbo",
      "price": 131,
      "listPrice": null,
      "currency": "UYU",
      "url": "https://www.disco.com.uy/product/galletas-avena-y-chocolate-nutrabien-175-g/601427"
    },
    {
      "super": "devoto",
      "sku": "601429",
      "name": "Galletas avena y manzana NUTRABIEN 175 g",
      "brand": "nutrabien",
      "group": "bimbo",
      "price": 131,
      "listPrice": null,
      "currency": "UYU",
      "url": "https://www.devoto.com.uy/product/galletas-avena-y-manzana-nutrabien-175-g/601429"
    },
    {
      "super": "disco",
      "sku": "601429",
      "name": "Galletas avena y manzana NUTRABIEN 175 g",
      "brand": "nutrabien",
      "group": "bimbo",
      "price": 131,
      "listPrice": null,
      "currency": "UYU",
      "url": "https://www.disco.com.uy/product/galletas-avena-y-manzana-nutrabien-175-g/601429"
    },
    {
      "super": "devoto",
      "sku": "601433",
      "name": "Galletas avena y pasas NUTRABIEN 175 g",
      "brand": "nutrabien",
      "group": "bimbo",
      "price": 131,
      "listPrice": null,
      "currency": "UYU",
      "url": "https://www.devoto.com.uy/product/galletas-avena-y-pasas-nutrabien-175-g/601433"
    },
    {
      "super": "disco",
      "sku": "601433",
      "name": "Galletas avena y pasas NUTRABIEN 175 g",
      "brand": "nutrabien",
      "group": "bimbo",
      "price": 131,
      "listPrice": null,
      "currency": "UYU",
      "url": "https://www.disco.com.uy/product/galletas-avena-y-pasas-nutrabien-175-g/601433"
    },
    {
      "super": "tiendainglesa",
      "sku": "1562145",
      "name": "Galletas NUTRA BIEN con Avena y Chocolate 175 gr",
      "brand": "nutrabien",
      "group": "bimbo",
      "price": 82,
      "listPrice": 136,
      "currency": "UYU",
      "url": "https://www.tiendainglesa.com.uy/supermercado/galletas-nutra-bien-con-avena-y-chocolate-175-gr.producto?1562145,,42"
    },
    {
      "super": "tata",
      "sku": "149198",
      "name": "Galletas Nutrabien Avena Y Chocolate 175 G",
      "brand": "nutrabien",
      "group": "bimbo",
      "price": 123,
      "listPrice": 123,
      "currency": "UYU",
      "url": "https://www.tata.com.uy/galletas-nutrabien-avena-y-chocolate-175-g-149198/p"
    },
    {
      "super": "tata",
      "sku": "149193",
      "name": "Galletas Nutrabien Avena Y Manzana 175 G",
      "brand": "nutrabien",
      "group": "bimbo",
      "price": 123,
      "listPrice": 123,
      "currency": "UYU",
      "url": "https://www.tata.com.uy/galletas-nutrabien-avena-y-manzana-175-g-149193/p"
    },
    {
      "super": "tata",
      "sku": "149194",
      "name": "Galletas Nutrabien Avena Y Pasas 175 G",
      "brand": "nutrabien",
      "group": "bimbo",
      "price": 123,
      "listPrice": 123,
      "currency": "UYU",
      "url": "https://www.tata.com.uy/galletas-nutrabien-avena-y-pasas-175-g-149194/p"
    },
    {
      "super": "devoto",
      "sku": "602053",
      "name": "Galletitas NUTRA BIEN Avena y Chocolate 75 g",
      "brand": "nutrabien",
      "group": "bimbo",
      "price": 79,
      "listPrice": null,
      "currency": "UYU",
      "url": "https://www.devoto.com.uy/product/galletitas-nutra-bien-avena-y-chocolate-75-g/602053"
    },
    {
      "super": "disco",
      "sku": "602053",
      "name": "Galletitas NUTRA BIEN Avena y Chocolate 75 g",
      "brand": "nutrabien",
      "group": "bimbo",
      "price": 79,
      "listPrice": null,
      "currency": "UYU",
      "url": "https://www.disco.com.uy/product/galletitas-nutra-bien-avena-y-chocolate-75-g/602053"
    },
    {
      "super": "devoto",
      "sku": "299690",
      "name": "Pan catalán 4 un.",
      "brand": "pancatalan",
      "group": "bimbo",
      "price": 95,
      "listPrice": null,
      "currency": "UYU",
      "url": "https://www.devoto.com.uy/product/pan-catalan-4-un/299690"
    },
    {
      "super": "disco",
      "sku": "299690",
      "name": "Pan catalán 4 un.",
      "brand": "pancatalan",
      "group": "bimbo",
      "price": 95,
      "listPrice": null,
      "currency": "UYU",
      "url": "https://www.disco.com.uy/product/pan-catalan-4-un/299690"
    },
    {
      "super": "tiendainglesa",
      "sku": "779",
      "name": "Pan Catalán TIENDA INGLESA 0% Grasas Trans 6 Unidades",
      "brand": "pancatalan",
      "group": "bimbo",
      "price": 139,
      "listPrice": null,
      "currency": "UYU",
      "url": "https://www.tiendainglesa.com.uy/supermercado/pan-catalan-tienda-inglesa-0%25-grasas-trans-6-unidades.producto?779,,42"
    },
    {
      "super": "tiendainglesa",
      "sku": "790",
      "name": "Pan Catalán TIENDA INGLESA x 1",
      "brand": "pancatalan",
      "group": "bimbo",
      "price": 30,
      "listPrice": null,
      "currency": "UYU",
      "url": "https://www.tiendainglesa.com.uy/supermercado/pan-catalan-tienda-inglesa-x-1.producto?790,,42"
    },
    {
      "super": "tiendainglesa",
      "sku": "1583467",
      "name": "Rapiditas BIMBO Chía Linaza (8 un.)",
      "brand": "rapiditas",
      "group": "bimbo",
      "price": 179,
      "listPrice": null,
      "currency": "UYU",
      "url": "https://www.tiendainglesa.com.uy/supermercado/rapiditas-bimbo-chia-linaza-8-un..producto?1583467,,42"
    },
    {
      "super": "tiendainglesa",
      "sku": "54733",
      "name": "Rapiditas BIMBO Light (10 un.)",
      "brand": "rapiditas",
      "group": "bimbo",
      "price": 179,
      "listPrice": null,
      "currency": "UYU",
      "url": "https://www.tiendainglesa.com.uy/supermercado/rapiditas-bimbo-light-10-un..producto?54733,,42"
    },
    {
      "super": "tata",
      "sku": "157041",
      "name": "Rapiditas Con Lino Y Chia Bimbo 8 U",
      "brand": "rapiditas",
      "group": "bimbo",
      "price": 145,
      "listPrice": 172,
      "currency": "UYU",
      "url": "https://www.tata.com.uy/rapiditas-con-lino-y-chia-bimbo-8-u-157041/p"
    },
    {
      "super": "tata",
      "sku": "806",
      "name": "Rapiditas Light Bimbo 10 U",
      "brand": "rapiditas",
      "group": "bimbo",
      "price": 145,
      "listPrice": 172,
      "currency": "UYU",
      "url": "https://www.tata.com.uy/rapiditas-light-bimbo-10-u-806/p"
    },
    {
      "super": "tata",
      "sku": "805",
      "name": "Rapiditas Tradicional Bimbo 10 U",
      "brand": "rapiditas",
      "group": "bimbo",
      "price": 145,
      "listPrice": 172,
      "currency": "UYU",
      "url": "https://www.tata.com.uy/rapiditas-tradicional-bimbo-10-u-805/p"
    },
    {
      "super": "tiendainglesa",
      "sku": "1514413",
      "name": "Tortilla Rapiditas Wrap XL BIMBO (6 un.) 420 g",
      "brand": "rapiditas",
      "group": "bimbo",
      "price": 199,
      "listPrice": null,
      "currency": "UYU",
      "url": "https://www.tiendainglesa.com.uy/supermercado/tortilla-rapiditas-wrap-xl-bimbo-6-un.-420-g.producto?1514413,,42"
    },
    {
      "super": "devoto",
      "sku": "664153",
      "name": "Tortillas rapiditas BIMBO 310 g",
      "brand": "rapiditas",
      "group": "bimbo",
      "price": 139,
      "listPrice": 168,
      "currency": "UYU",
      "url": "https://www.devoto.com.uy/product/tortillas-rapiditas-bimbo-310-g/664153"
    },
    {
      "super": "disco",
      "sku": "664153",
      "name": "Tortillas rapiditas BIMBO 310 g",
      "brand": "rapiditas",
      "group": "bimbo",
      "price": 139,
      "listPrice": 168,
      "currency": "UYU",
      "url": "https://www.disco.com.uy/product/tortillas-rapiditas-bimbo-310-g/664153"
    },
    {
      "super": "devoto",
      "sku": "664154",
      "name": "Tortillas rapiditas BIMBO light 310 g",
      "brand": "rapiditas",
      "group": "bimbo",
      "price": 139,
      "listPrice": 168,
      "currency": "UYU",
      "url": "https://www.devoto.com.uy/product/tortillas-rapiditas-bimbo-light-310-g/664154"
    },
    {
      "super": "disco",
      "sku": "664154",
      "name": "Tortillas rapiditas BIMBO light 310 g",
      "brand": "rapiditas",
      "group": "bimbo",
      "price": 139,
      "listPrice": 168,
      "currency": "UYU",
      "url": "https://www.disco.com.uy/product/tortillas-rapiditas-bimbo-light-310-g/664154"
    },
    {
      "super": "devoto",
      "sku": "373987",
      "name": "Tortillas Rapiditas BIMBO Lino Chía 250 g",
      "brand": "rapiditas",
      "group": "bimbo",
      "price": 139,
      "listPrice": null,
      "currency": "UYU",
      "url": "https://www.devoto.com.uy/product/tortillas-rapiditas-bimbo-lino-chia-250-g/373987"
    },
    {
      "super": "disco",
      "sku": "373987",
      "name": "Tortillas Rapiditas BIMBO Lino Chía 250 g",
      "brand": "rapiditas",
      "group": "bimbo",
      "price": 139,
      "listPrice": null,
      "currency": "UYU",
      "url": "https://www.disco.com.uy/product/tortillas-rapiditas-bimbo-lino-chia-250-g/373987"
    },
    {
      "super": "tata",
      "sku": "86711",
      "name": "Tortillas Rapiditas Bimbo Maxi 6 U 420 G",
      "brand": "rapiditas",
      "group": "bimbo",
      "price": 175,
      "listPrice": 175,
      "currency": "UYU",
      "url": "https://www.tata.com.uy/tortillas-rapiditas-bimbo-maxi-6-u-420-g-86711/p"
    },
    {
      "super": "devoto",
      "sku": "345155",
      "name": "Tortillas rapiditas BIMBO maxi 6 un. 420 g",
      "brand": "rapiditas",
      "group": "bimbo",
      "price": 193,
      "listPrice": null,
      "currency": "UYU",
      "url": "https://www.devoto.com.uy/product/tortillas-rapiditas-bimbo-maxi-6-un-420-g/345155"
    },
    {
      "super": "disco",
      "sku": "345155",
      "name": "Tortillas rapiditas BIMBO maxi 6 un. 420 g",
      "brand": "rapiditas",
      "group": "bimbo",
      "price": 193,
      "listPrice": null,
      "currency": "UYU",
      "url": "https://www.disco.com.uy/product/tortillas-rapiditas-bimbo-maxi-6-un-420-g/345155"
    },
    {
      "super": "tata",
      "sku": "157010",
      "name": "Nachos Clasicos San Exp Sanisimo 160 G",
      "brand": "sanissimo",
      "group": "bimbo",
      "price": 227,
      "listPrice": 227,
      "currency": "UYU",
      "url": "https://www.tata.com.uy/nachos-clasicos-san-exp-sanisimo-160-g-157010/p"
    },
    {
      "super": "tata",
      "sku": "157011",
      "name": "Nachos Tomate Alba San Sanisimo 160 G",
      "brand": "sanissimo",
      "group": "bimbo",
      "price": 227,
      "listPrice": 227,
      "currency": "UYU",
      "url": "https://www.tata.com.uy/nachos-tomate-alba-san-sanisimo-160-g-157011/p"
    },
    {
      "super": "tata",
      "sku": "86714",
      "name": "Tostadas De Maiz  Salmas Sanissimo 6 U 108 G",
      "brand": "sanissimo",
      "group": "bimbo",
      "price": 180,
      "listPrice": 180,
      "currency": "UYU",
      "url": "https://www.tata.com.uy/tostadas-de-maiz-salmas-sanissimo-6-u-108-g-86714/p"
    },
    {
      "super": "tata",
      "sku": "148195",
      "name": "Tostadas Salmas Horneadas 216 G",
      "brand": "sanissimo",
      "group": "bimbo",
      "price": 261,
      "listPrice": 261,
      "currency": "UYU",
      "url": "https://www.tata.com.uy/tostadas-salmas-horneadas-216-g-148195/p"
    },
    {
      "super": "tiendainglesa",
      "sku": "1516028",
      "name": "Tostadita Salmas de Maíz al Horno SANISSIMO 216 gr",
      "brand": "sanissimo",
      "group": "bimbo",
      "price": 186,
      "listPrice": 310,
      "currency": "UYU",
      "url": "https://www.tiendainglesa.com.uy/supermercado/tostadita-salmas-de-maiz-al-horno-sanissimo-216-gr.producto?1516028,,42&campaign=search_facets"
    },
    {
      "super": "tiendainglesa",
      "sku": "1516029",
      "name": "Tostadita Salmas de Maíz al Horno SANISSIMO 6 Unidades",
      "brand": "sanissimo",
      "group": "bimbo",
      "price": 109,
      "listPrice": 182,
      "currency": "UYU",
      "url": "https://www.tiendainglesa.com.uy/supermercado/tostadita-salmas-de-maiz-al-horno-sanissimo-6-unidades.producto?1516029,,42"
    },
    {
      "super": "devoto",
      "sku": "664235",
      "name": "Tostaditas SANISSIMO salmas x 12 un. 216 g",
      "brand": "sanissimo",
      "group": "bimbo",
      "price": 275,
      "listPrice": null,
      "currency": "UYU",
      "url": "https://www.devoto.com.uy/product/tostaditas-sanissimo-salmas-x-12-un-216-g/664235"
    },
    {
      "super": "disco",
      "sku": "664235",
      "name": "Tostaditas SANISSIMO salmas x 12 un. 216 g",
      "brand": "sanissimo",
      "group": "bimbo",
      "price": 275,
      "listPrice": null,
      "currency": "UYU",
      "url": "https://www.disco.com.uy/product/tostaditas-sanissimo-salmas-x-12-un-216-g/664235"
    },
    {
      "super": "disco",
      "sku": "664234",
      "name": "Tostaditas SANISSIMO salmas x 5 un. 90 g",
      "brand": "sanissimo",
      "group": "bimbo",
      "price": 168,
      "listPrice": null,
      "currency": "UYU",
      "url": "https://www.disco.com.uy/product/tostaditas-sanissimo-salmas-x-5-un-90-g/664234"
    },
    {
      "super": "devoto",
      "sku": "602183",
      "name": "Tostaditas SANISSIMO Salmas x 6 108 g",
      "brand": "sanissimo",
      "group": "bimbo",
      "price": 176,
      "listPrice": null,
      "currency": "UYU",
      "url": "https://www.devoto.com.uy/product/tostaditas-sanissimo-salmas-x-6-108-g/602183"
    },
    {
      "super": "disco",
      "sku": "602183",
      "name": "Tostaditas SANISSIMO Salmas x 6 108 g",
      "brand": "sanissimo",
      "group": "bimbo",
      "price": 176,
      "listPrice": null,
      "currency": "UYU",
      "url": "https://www.disco.com.uy/product/tostaditas-sanissimo-salmas-x-6-108-g/602183"
    },
    {
      "super": "tiendainglesa",
      "sku": "309761",
      "name": "Fajitas TÍA ROSA x 10 Unidades 215 gr",
      "brand": "tia rosa",
      "group": "bimbo",
      "price": 164,
      "listPrice": null,
      "currency": "UYU",
      "url": "https://www.tiendainglesa.com.uy/supermercado/fajitas-tia-rosa-x-10-unidades-215-gr.producto?309761,,42"
    },
    {
      "super": "devoto",
      "sku": "981159",
      "name": "Tortillas Burrera TÍA ROSA 420 g",
      "brand": "tia rosa",
      "group": "bimbo",
      "price": 179,
      "listPrice": null,
      "currency": "UYU",
      "url": "https://www.devoto.com.uy/product/tortillas-burrera-tia-rosa-420-g/981159"
    },
    {
      "super": "disco",
      "sku": "981159",
      "name": "Tortillas Burrera TÍA ROSA 420 g",
      "brand": "tia rosa",
      "group": "bimbo",
      "price": 179,
      "listPrice": null,
      "currency": "UYU",
      "url": "https://www.disco.com.uy/product/tortillas-burrera-tia-rosa-420-g/981159"
    },
    {
      "super": "tiendainglesa",
      "sku": "1595670",
      "name": "Tortillas Burreras TÍA ROSA 420 gr",
      "brand": "tia rosa",
      "group": "bimbo",
      "price": 192,
      "listPrice": null,
      "currency": "UYU",
      "url": "https://www.tiendainglesa.com.uy/supermercado/tortillas-burreras-tia-rosa-420-gr.producto?1595670,,42"
    },
    {
      "super": "devoto",
      "sku": "981158",
      "name": "Tortillas Fajitas TÍA ROSA 240 g",
      "brand": "tia rosa",
      "group": "bimbo",
      "price": 153,
      "listPrice": null,
      "currency": "UYU",
      "url": "https://www.devoto.com.uy/product/tortillas-fajitas-tia-rosa-240-g/981158"
    },
    {
      "super": "disco",
      "sku": "981158",
      "name": "Tortillas Fajitas TÍA ROSA 240 g",
      "brand": "tia rosa",
      "group": "bimbo",
      "price": 153,
      "listPrice": null,
      "currency": "UYU",
      "url": "https://www.disco.com.uy/product/tortillas-fajitas-tia-rosa-240-g/981158"
    },
    {
      "super": "tata",
      "sku": "169928",
      "name": "Tortillas Harina Burrera Tia Rosa 420 Gr",
      "brand": "tia rosa",
      "group": "bimbo",
      "price": 169,
      "listPrice": 169,
      "currency": "UYU",
      "url": "https://www.tata.com.uy/tortillas-harina-burrera-tia-rosa-420-gr-169928/p"
    },
    {
      "super": "tata",
      "sku": "169942",
      "name": "Tortillas Harina De Trigo Fajitas Tia Rosa 240 Gr",
      "brand": "tia rosa",
      "group": "bimbo",
      "price": 149,
      "listPrice": 149,
      "currency": "UYU",
      "url": "https://www.tata.com.uy/tortillas-harina-de-trigo-fajitas-tia-rosa-240-gr-169942/p"
    },
    {
      "super": "devoto",
      "sku": "573956",
      "name": "Tortillas mexicanas TÍA ROSA 270 g",
      "brand": "tia rosa",
      "group": "bimbo",
      "price": 153,
      "listPrice": null,
      "currency": "UYU",
      "url": "https://www.devoto.com.uy/product/tortillas-mexicanas-tia-rosa-270-g/573956"
    },
    {
      "super": "disco",
      "sku": "573956",
      "name": "Tortillas mexicanas TÍA ROSA 270 g",
      "brand": "tia rosa",
      "group": "bimbo",
      "price": 153,
      "listPrice": null,
      "currency": "UYU",
      "url": "https://www.disco.com.uy/product/tortillas-mexicanas-tia-rosa-270-g/573956"
    },
    {
      "super": "tiendainglesa",
      "sku": "1562711",
      "name": "Tortillas Taqueras TÍA ROSA x 8 Unidades 270 gr",
      "brand": "tia rosa",
      "group": "bimbo",
      "price": 158,
      "listPrice": null,
      "currency": "UYU",
      "url": "https://www.tiendainglesa.com.uy/supermercado/tortillas-taqueras-tia-rosa-x-8-unidades-270-gr.producto?1562711,,42"
    },
    {
      "super": "tata",
      "sku": "136884",
      "name": "Pan Bimbo Mix Cereales Vital 540 G",
      "brand": "vital",
      "group": "bimbo",
      "price": 215,
      "listPrice": 215,
      "currency": "UYU",
      "url": "https://www.tata.com.uy/pan-bimbo-mix-cereales-vital-540-g-136884/p"
    },
    {
      "super": "devoto",
      "sku": "201109",
      "name": "Pan con semillas BIMBO vital 540 g",
      "brand": "vital",
      "group": "bimbo",
      "price": 225,
      "listPrice": null,
      "currency": "UYU",
      "url": "https://www.devoto.com.uy/product/pan-con-semillas-bimbo-vital-540-g/201109"
    },
    {
      "super": "disco",
      "sku": "201109",
      "name": "Pan con semillas BIMBO vital 540 g",
      "brand": "vital",
      "group": "bimbo",
      "price": 225,
      "listPrice": null,
      "currency": "UYU",
      "url": "https://www.disco.com.uy/product/pan-con-semillas-bimbo-vital-540-g/201109"
    },
    {
      "super": "tiendainglesa",
      "sku": "1533462",
      "name": "Pan Mix Cereales VITAL Bimbo 510 gr",
      "brand": "vital",
      "group": "bimbo",
      "price": 227,
      "listPrice": null,
      "currency": "UYU",
      "url": "https://www.tiendainglesa.com.uy/supermercado/pan-mix-cereales-vital-bimbo-510-gr.producto?1533462,,42"
    },
    {
      "super": "devoto",
      "sku": "661373",
      "name": "Pan mix de cerales Vital BIMBO 540 g",
      "brand": "vital",
      "group": "bimbo",
      "price": 225,
      "listPrice": null,
      "currency": "UYU",
      "url": "https://www.devoto.com.uy/product/pan-mix-de-cerales-vital-bimbo-540-g/661373"
    },
    {
      "super": "disco",
      "sku": "661373",
      "name": "Pan mix de cerales Vital BIMBO 540 g",
      "brand": "vital",
      "group": "bimbo",
      "price": 225,
      "listPrice": null,
      "currency": "UYU",
      "url": "https://www.disco.com.uy/product/pan-mix-de-cerales-vital-bimbo-540-g/661373"
    },
    {
      "super": "tata",
      "sku": "804",
      "name": "Pan Semillas Vital Bimbo 510 G",
      "brand": "vital",
      "group": "bimbo",
      "price": 215,
      "listPrice": 215,
      "currency": "UYU",
      "url": "https://www.tata.com.uy/pan-semillas-vital-bimbo-510-g-804/p"
    }
  ]
}